Metadata-Version: 1.0
Name: django-key-generator
Version: 1.0.3
Summary: A django-admin command to generate a secret key
Home-page: https://github.com/TrianglePlusPlus/django-key-generator
Author: Triangle++
Author-email: justice.suh@gmail.com
License: MIT
Platform: UNKNOWN
